mcp_ad_server/__init__.py
mcp_ad_server/config.py
mcp_ad_server/main.py
mcp_ad_server/data/games/48.json
mcp_ad_server/data/games/59.json
mcp_ad_server/data/games/61.json
mcp_ad_server/data/games/78.json
mcp_ad_server/data/groups/1_投放启动决策指标组.json
mcp_ad_server/data/groups/2_投放效果实时监控指标组.json
mcp_ad_server/data/groups/3_短期价值评估指标组(首日-7日).json
mcp_ad_server/data/groups/4_深度价值与留存指标组.json
mcp_ad_server/data/groups/5_平台数据对账指标组.json
mcp_ad_server/data/groups/6_终止决策预警指标组.json
mcp_ad_server/data/groups/7_财务核算指标组.json
mcp_ad_server/data/indicators/24小时ROI.json
mcp_ad_server/data/indicators/3秒播放率.json
mcp_ad_server/data/indicators/7日ROI.json
mcp_ad_server/data/indicators/cid.json
mcp_ad_server/data/indicators/cid备注.json
mcp_ad_server/data/indicators/一键起量消耗.json
mcp_ad_server/data/indicators/一阶段花费.json
mcp_ad_server/data/indicators/二阶段花费.json
mcp_ad_server/data/indicators/付费分成后累计ROI.json
mcp_ad_server/data/indicators/付费分成后首日ROI.json
mcp_ad_server/data/indicators/付费成本.json
mcp_ad_server/data/indicators/付费累计ROI.json
mcp_ad_server/data/indicators/付费首日ROI.json
mcp_ad_server/data/indicators/低质原因.json
mcp_ad_server/data/indicators/分成后累计ROI.json
mcp_ad_server/data/indicators/分成后累计平台ROI.json
mcp_ad_server/data/indicators/分成后首日ROI.json
mcp_ad_server/data/indicators/分成后首日平台ROI.json
mcp_ad_server/data/indicators/创意人.json
mcp_ad_server/data/indicators/创意名称.json
mcp_ad_server/data/indicators/创角成本.json
mcp_ad_server/data/indicators/创角率.json
mcp_ad_server/data/indicators/制作人.json
mcp_ad_server/data/indicators/千次展现均价.json
mcp_ad_server/data/indicators/备注.json
mcp_ad_server/data/indicators/完播率.json
mcp_ad_server/data/indicators/小游戏广告变现金额（平台上报）.json
mcp_ad_server/data/indicators/小游戏注册首日广告变现ROI.json
mcp_ad_server/data/indicators/小游戏注册首日广告变现金额.json
mcp_ad_server/data/indicators/平台当日付费次数.json
mcp_ad_server/data/indicators/平台当日充值.json
mcp_ad_server/data/indicators/平台当日充值人数.json
mcp_ad_server/data/indicators/平台新增付费人数.json
mcp_ad_server/data/indicators/平台新增付费金额.json
dartou_mcp_ad_server-0.0.3.dist-info/METADATA
dartou_mcp_ad_server-0.0.3.dist-info/WHEEL
dartou_mcp_ad_server-0.0.3.dist-info/entry_points.txt
dartou_mcp_ad_server-0.0.3.dist-info/top_level.txt
dartou_mcp_ad_server-0.0.3.dist-info/RECORD
